forest/__init__.py
forest/metrics.py
forest/tree_exceptions.py
forest/binary_trees/__init__.py
forest/binary_trees/atomic_trees.py
forest/binary_trees/avl_tree.py
forest/binary_trees/binary_search_tree.py
forest/binary_trees/double_threaded_binary_tree.py
forest/binary_trees/red_black_tree.py
forest/binary_trees/single_threaded_binary_trees.py
forest/binary_trees/traversal.py
forest_python-0.6.3.dist-info/LICENSE
forest_python-0.6.3.dist-info/METADATA
forest_python-0.6.3.dist-info/WHEEL
forest_python-0.6.3.dist-info/top_level.txt
forest_python-0.6.3.dist-info/RECORD
