Metadata-Version: 2.1
Name: forest-python
Version: 0.6.3
Summary: The Forest Project in Python
Author-email: Shun Huang <shun@formosa1544.com>
License: MIT License
Project-URL: repository, https://github.com/burpeesDaily/forest-python
Keywords: tree,data-structures
Classifier: License :: OSI Approved :: MIT License
Classifier: Programming Language :: Python
Requires-Python: >=3.9
License-File: LICENSE
